energy_pandas/__init__.py
energy_pandas/edf_utils.py
energy_pandas/energypandas.py
energy_pandas/energyplus_en.txt
energy_pandas/plotting.py
energy_pandas/units.py
energy_pandas-0.4.1.dist-info/LICENSE.md
energy_pandas-0.4.1.dist-info/METADATA
energy_pandas-0.4.1.dist-info/WHEEL
energy_pandas-0.4.1.dist-info/RECORD
