Metadata-Version: 2.1
Name: energy_pandas
Version: 0.4.1
Summary: Building Energy pandas extension
Home-page: https://github.com/samuelduchesne/energy-pandas
Author: Samuel Letellier-Duchesne
Author-email: fsamuelduchesne@me.com
Requires-Python: >=3.9,<4.0
Classifier: Programming Language :: Python :: 3
Classifier: Programming Language :: Python :: 3.9
Classifier: Programming Language :: Python :: 3.10
Classifier: Programming Language :: Python :: 3.11
Classifier: Programming Language :: Python :: 3.12
Requires-Dist: matplotlib (>=3.9.2,<4.0.0)
Requires-Dist: numpy (>=2.0.2,<3.0.0) ; python_full_version <= "3.9.0"
Requires-Dist: numpy (>=2.1.1,<3.0.0) ; python_version == "3.10"
Requires-Dist: outdated (>=0.2.2,<0.3.0)
Requires-Dist: pandas (>=2.2.2,<3.0.0)
Requires-Dist: pint (>=0.24.3,<0.25.0)
Requires-Dist: scikit-learn (>=1.5.2,<2.0.0)
Requires-Dist: tabulate (>=0.9.0,<0.10.0)
Requires-Dist: tqdm (>=4.66.5,<5.0.0)
Requires-Dist: tsam (>=2.3.3,<3.0.0)
Project-URL: Documentation, https://samuelduchesne.github.io/energy-pandas/
Project-URL: Repository, https://github.com/samuelduchesne/energy-pandas
